altasigma/__init__.py
altasigma/initialize.py
altasigma/config/__init__.py
altasigma/config/config.py
altasigma/config/http_session.py
altasigma/credentials/__init__.py
altasigma/credentials/credential_utils.py
altasigma/credentials/token_refresher.py
altasigma/io/__init__.py
altasigma/io/augurdata.py
altasigma/io/data_management.py
altasigma/io/files.py
altasigma/jobsupervisor/__init__.py
altasigma/jobsupervisor/job_supervisor_abstract.py
altasigma/jobsupervisor/job_supervisor_dev_mock.py
altasigma/jobsupervisor/job_supervisor_helpers.py
altasigma/jobsupervisor/job_supervisor_http.py
altasigma/jobsupervisor/reports.py
altasigma/progress_reporter/__init__.py
altasigma/progress_reporter/progress_reporter.py
altasigma/spark_session/__init__.py
altasigma/spark_session/spark_session_util.py
altasigma/utils/__init__.py
altasigma/utils/notebook.py
altasigma-3.10.4.dist-info/licenses/LICENSE
altasigma-3.10.4.dist-info/METADATA
altasigma-3.10.4.dist-info/WHEEL
altasigma-3.10.4.dist-info/top_level.txt
altasigma-3.10.4.dist-info/RECORD
