Metadata-Version: 2.4
Name: altasigma
Version: 3.10.4
Summary: Python helpers for data science and ML workflows on the AltaSigma AI platform
Home-page: https://www.altasigma.com
Author: AltaSigma GmbH
Author-email: pypi@altasigma.com
License: Proprietary
Classifier: License :: Other/Proprietary License
Classifier: Programming Language :: Python :: 3
Classifier: Programming Language :: Python :: 3.10
Classifier: Programming Language :: Python :: 3.11
Requires-Python: >=3.10
License-File: LICENSE
Requires-Dist: requests<3,>=2
Requires-Dist: pandas>=1
Requires-Dist: ipython>=8
Requires-Dist: boto3<2,>=1.18.49
Dynamic: author
Dynamic: author-email
Dynamic: classifier
Dynamic: description
Dynamic: description-content-type
Dynamic: home-page
Dynamic: license
Dynamic: license-file
Dynamic: requires-dist
Dynamic: requires-python
Dynamic: summary
